glassgen/__init__.py
glassgen/config.py
glassgen/interface.py
glassgen/generator/__init__.py
glassgen/generator/batch_controller.py
glassgen/generator/duplication.py
glassgen/generator/generator.py
glassgen/generator/generators.py
glassgen/schema/__init__.py
glassgen/schema/base.py
glassgen/schema/schema.py
glassgen/schema/user_schema.py
glassgen/sinks/__init__.py
glassgen/sinks/base.py
glassgen/sinks/csv_sink.py
glassgen/sinks/kafka_sink.py
glassgen/sinks/webhook_sink.py
glassgen/sinks/yield_sink.py
glassgen-0.2.4.dist-info/METADATA
glassgen-0.2.4.dist-info/WHEEL
glassgen-0.2.4.dist-info/entry_points.txt
glassgen-0.2.4.dist-info/licenses/LICENSE
glassgen-0.2.4.dist-info/RECORD
