Metadata-Version: 2.4
Name: glassgen
Version: 0.2.4
Summary: A flexible synthetic data generation service
Project-URL: Homepage, https://glassgen.glassflow.dev/
Project-URL: Documentation, https://glassgen.glassflow.dev/
Project-URL: Repository, https://github.com/glassflow/glassgen.git
Project-URL: Issues, https://github.com/glassflow/glassgen/issues
Author-email: GlassFlow <hello@glassflow.dev>
License: MIT
License-File: LICENSE
Keywords: csv,data-generation,kafka,synthetic-data,testing
Classifier: Development Status :: 4 - Beta
Classifier: Intended Audience :: Developers
Classifier: License :: OSI Approved :: MIT License
Classifier: Programming Language :: Python :: 3
Classifier: Programming Language :: Python :: 3.8
Classifier: Programming Language :: Python :: 3.9
Classifier: Programming Language :: Python :: 3.10
Classifier: Programming Language :: Python :: 3.11
Classifier: Topic :: Software Development :: Libraries :: Python Modules
Requires-Python: >=3.8
Requires-Dist: click>=8.0.0
Requires-Dist: confluent-kafka==2.8.2
Requires-Dist: faker>=19.0.0
Requires-Dist: pydantic>=2.0.0
Requires-Dist: requests>=2.25.0
Provides-Extra: dev
Requires-Dist: mypy>=1.0.0; extra == 'dev'
Requires-Dist: pytest-cov>=5.0.0; extra == 'dev'
Requires-Dist: pytest>=8.0.0; extra == 'dev'
Requires-Dist: ruff>=0.11.0; extra == 'dev'
